odoo/addons/stock_picking_report_delivery_driver/README.rst
odoo/addons/stock_picking_report_delivery_driver/__init__.py
odoo/addons/stock_picking_report_delivery_driver/__manifest__.py
odoo/addons/stock_picking_report_delivery_driver/i18n/es.po
odoo/addons/stock_picking_report_delivery_driver/i18n/it.po
odoo/addons/stock_picking_report_delivery_driver/i18n/stock_picking_report_delivery_driver.pot
odoo/addons/stock_picking_report_delivery_driver/readme/CONTRIBUTORS.md
odoo/addons/stock_picking_report_delivery_driver/readme/DESCRIPTION.md
odoo/addons/stock_picking_report_delivery_driver/readme/USAGE.md
odoo/addons/stock_picking_report_delivery_driver/report/report_deliveryslip.xml
odoo/addons/stock_picking_report_delivery_driver/report/report_stockpicking_operations.xml
odoo/addons/stock_picking_report_delivery_driver/static/description/icon.png
odoo/addons/stock_picking_report_delivery_driver/static/description/index.html
odoo_addon_stock_picking_report_delivery_driver-18.0.1.0.1.dist-info/METADATA
odoo_addon_stock_picking_report_delivery_driver-18.0.1.0.1.dist-info/WHEEL
odoo_addon_stock_picking_report_delivery_driver-18.0.1.0.1.dist-info/top_level.txt
odoo_addon_stock_picking_report_delivery_driver-18.0.1.0.1.dist-info/RECORD
